Workbook

Sheet Read Me
A1: RetailzPOS — 90-Day Content Calendar & Tracker
A2: Launch quarter · 3 August – 1 November 2026 · United States · v1.0
A5: What this workbook is
A6: The production and performance system behind the 90-Day Marketing Plan and Content Book. Every row on the 90-Day Calendar & Tracker sheet is one platform-specific post, exploded from the 89 creative units written in full in the Content Book.
A8: How a unit becomes multiple rows
A9: Each Content Book unit runs on 1-6 platforms depending on format (a blog anchor runs on LinkedIn, Facebook, the blog itself, and mirrors to X; a Reel runs on TikTok primary and mirrors to Instagram). Each platform instance gets its own row so status and performance can be tracked independently, tagged Primary / Adapted / Mirror to show which role that platform plays for the unit.
A11: Sheet guide
A12: 90-Day Calendar & Tracker — the master sheet. One row per platform-specific post, band-grouped into PLAN (what/who/why), PRODUCTION (status/ownership/pre-publish score), PUBLISHED (when/where it actually went live), and PERFORMANCE (the numbers once it has).
A13: Platform Metric Guide — how a Like on one platform compares to a Save on another, so performance is judged fairly across channels.
A14: Performance Dashboard — top-line, mostly auto-summarizing rollups pulled from the master sheet.
A15: Weekly Themes — the 13-week mindset-ladder map from the Plan, one row per week.
A16: Content Mix Tracker — live counts of what's actually shipped, by pillar / format / platform / persona, against the Plan's target mix.
... A26: Pricing is never published. No post, no comment reply, no cell in this workbook should ever contain a dollar figure, a range, or a soft price anchor. See the Do & Don't sheet and Plan Section 2.

Sheet 90-Day Calendar & Tracker
A1: RetailzPOS — 90-Day Calendar & Tracker
A2: One row per platform-specific post, exploded from the 89 Content Book units.
A4: PLAN | P4: PRODUCTION | Y4: PUBLISHED | AC4: PERFORMANCE
A5: Post ID | B5: Unit ID | C5: Week | D5: Publish Date | E5: Day of Week | F5: Persona | G5: Messaging Pillar | H5: Content Category | I5: Format Group | J5: Platform | K5: Role | L5: Title / Hook | M5: CTA Type | N5: Compliance Review Required | O5: Rights Clearance Required | P5: Copy Status | Q5: Design Status | R5: Copy Owner | S5: Design Owner | T5: Reviewer | U5: Pre-publish Score (/100) | V5: Pre-publish Gate Passed | W5: Scheduled Date | X5: Scheduled Time | Y5: Publish Status | Z5: Actual Publish Date | AA5: Live URL | AB5: Published By | AC5: Reach | AD5: Impressions | AE5: Likes/Reactions | AF5: Comments | AG5: Shares | AH5: Saves | AI5: Video Views | AJ5: Watch-through % | AK5: Link Clicks | AL5: Demo Requests Attributed | AM5: Boosted (Paid) | AN5: Normalized Engagement Score | AO5: 30-Day Format Median (Reach) | AP5: Reach Multiplier | AQ5: Post Grade | AR5: Persona Match Confirmed | AS5: Compliance Sign-off Date | AT5: Notes / Follow-up
A6: PRE-U1-FA | B6: PRE-U1 | C6: PRE | D6: 46234 | E6: Friday | F6: All | G6: Built for what needs an ID check. | H6: Promote | I6: Static | J6: Facebook | K6: Primary | L6: Profile bios go live | M6: Book a demo | N6: No | O6: No | P6: Not started | Q6: Not started | V6: =IF(U6="","",IF(U6>=70,"Pass","Hold")) | W6: 46234 | X6: 10:00 AM | Y6: Scheduled | AM6: No | AP6: =IF(AND(AC6<>"",AO6<>"",AO6>0),AC6/AO6,"") | AQ6: =IF(AP6="","",IF(AP6>=2,"A",IF(AP6>=1.2,"B",IF(AP6>=0.6,"C","D"))))
A7: PRE-U1-IN | B7: PRE-U1 | C7: PRE | D7: 46234 | E7: Friday | F7: All | G7: Built for what needs an ID check. | H7: Promote | I7: Static | J7: Instagram | K7: Primary | L7: Profile bios go live | M7: Book a demo | N7: No | O7: No | P7: Not started | Q7: Not started | V7: =IF(U7="","",IF(U7>=70,"Pass","Hold")) | W7: 46234 | X7: 10:00 AM | Y7: Scheduled | AM7: No | AP7: =IF(AND(AC7<>"",AO7<>"",AO7>0),AC7/AO7,"") | AQ7: =IF(AP7="","",IF(AP7>=2,"A",IF(AP7>=1.2,"B",IF(AP7>=0.6,"C","D"))))
A8: PRE-U1-LI | B8: PRE-U1 | C8: PRE | D8: 46234 | E8: Friday | F8: All | G8: Built for what needs an ID check. | H8: Promote | I8: Static | J8: LinkedIn | K8: Primary | L8: Profile bios go live | M8: Book a demo | N8: No | O8: No | P8: Not started | Q8: Not started | V8: =IF(U8="","",IF(U8>=70,"Pass","Hold")) | W8: 46234 | X8: 10:00 AM | Y8: Scheduled | AM8: No | AP8: =IF(AND(AC8<>"",AO8<>"",AO8>0),AC8/AO8,"") | AQ8: =IF(AP8="","",IF(AP8>=2,"A",IF(AP8>=1.2,"B",IF(AP8>=0.6,"C","D"))))
A9: PRE-U1-TI | B9: PRE-U1 | C9: PRE | D9: 46234 | E9: Friday | F9: All | G9: Built for what needs an ID check. | H9: Promote | I9: Static | J9: TikTok | K9: Primary | L9: Profile bios go live | M9: Book a demo | N9: No | O9: No | P9: Not started | Q9: Not started | V9: =IF(U9="","",IF(U9>=70,"Pass","Hold")) | W9: 46234 | X9: 10:00 AM | Y9: Scheduled | AM9: No | AP9: =IF(AND(AC9<>"",AO9<>"",AO9>0),AC9/AO9,"") | AQ9: =IF(AP9="","",IF(AP9>=2,"A",IF(AP9>=1.2,"B",IF(AP9>=0.6,"C","D"))))
A10: PRE-U1-X | B10: PRE-U1 | C10: PRE | D10: 46234 | E10: Friday | F10: All | G10: Built for what needs an ID check. | H10: Promote | I10: Static | J10: X | K10: Mirror | L10: Profile bios go live | M10: Book a demo | N10: No | O10: No | P10: Not started | Q10: Not started | V10: =IF(U10="","",IF(U10>=70,"Pass","Hold")) | W10: 46234 | X10: 10:00 AM | Y10: Scheduled | AM10: No | AP10: =IF(AND(AC10<>"",AO10<>"",AO10>0),AC10/AO10,"") | AQ10: =IF(AP10="","",IF(AP10>=2,"A",IF(AP10>=1.2,"B",IF(AP10>=0.6,"C","D"))))
A11: PRE-U1-TH | B11: PRE-U1 | C11: PRE | D11: 46234 | E11: Friday | F11: All | G11: Built for what needs an ID check. | H11: Promote | I11: Static | J11: Threads | K11: Mirror | L11: Profile bios go live | M11: Book a demo | N11: No | O11: No | P11: Not started | Q11: Not started | V11: =IF(U11="","",IF(U11>=70,"Pass","Hold")) | W11: 46234 | X11: 10:00 AM | Y11: Scheduled | AM11: No | AP11: =IF(AND(AC11<>"",AO11<>"",AO11>0),AC11/AO11,"") | AQ11: =IF(AP11="","",IF(AP11>=2,"A",IF(AP11>=1.2,"B",IF(AP11>=0.6,"C","D"))))
A12: PRE-U2-LI | B12: PRE-U2 | C12: PRE | D12: 46235 | E12: Saturday | F12: All | G12: A quote built around your store, not a shelf price. | H12: Promote | I12: Static | J12: LinkedIn | K12: Primary | L12: Review-site profiles claimed | M12: Book a demo | N12: No | O12: No | P12: Not started | Q12: Not started | V12: =IF(U12="","",IF(U12>=70,"Pass","Hold")) | W12: 46235 | X12: 10:00 AM | Y12: Scheduled | AM12: No | AP12: =IF(AND(AC12<>"",AO12<>"",AO12>0),AC12/AO12,"") | AQ12: =IF(AP12="","",IF(AP12>=2,"A",IF(AP12>=1.2,"B",IF(AP12>=0.6,"C","D"))))
A13: PRE-U2-FA | B13: PRE-U2 | C13: PRE | D13: 46235 | E13: Saturday | F13: All | G13: A quote built around your store, not a shelf price. | H13: Promote | I13: Static | J13: Facebook | K13: Mirror | L13: Review-site profiles claimed | M13: Book a demo | N13: No | O13: No | P13: Not started | Q13: Not started | V13: =IF(U13="","",IF(U13>=70,"Pass","Hold")) | W13: 46235 | X13: 10:00 AM | Y13: Scheduled | AM13: No | AP13: =IF(AND(AC13<>"",AO13<>"",AO13>0),AC13/AO13,"") | AQ13: =IF(AP13="","",IF(AP13>=2,"A",IF(AP13>=1.2,"B",IF(AP13>=0.6,"C","D"))))
A14: PRE-U2-IN | B14: PRE-U2 | C14: PRE | D14: 46235 | E14: Saturday | F14: All | G14: A quote built around your store, not a shelf price. | H14: Promote | I14: Static | J14: Instagram | K14: Adapted | L14: Review-site profiles claimed | M14: Book a demo | N14: No | O14: No | P14: Not started | Q14: Not started | V14: =IF(U14="","",IF(U14>=70,"Pass","Hold")) | W14: 46235 | X14: 10:00 AM | Y14: Scheduled | AM14: No | AP14: =IF(AND(AC14<>"",AO14<>"",AO14>0),AC14/AO14,"") | AQ14: =IF(AP14="","",IF(AP14>=2,"A",IF(AP14>=1.2,"B",IF(AP14>=0.6,"C","D"))))
A15: PRE-U3-TI | B15: PRE-U3 | C15: PRE | D15: 46236 | E15: Sunday | F15: All | G15: Built for what needs an ID check. | H15: Promote | I15: Video | J15: TikTok | K15: Primary | L15: Product tour teaser | M15: Book a demo | N15: No | O15: No | P15: Not started | Q15: Not started | V15: =IF(U15="","",IF(U15>=70,"Pass","Hold")) | W15: 46236 | X15: 10:00 AM | Y15: Scheduled | AM15: No | AP15: =IF(AND(AC15<>"",AO15<>"",AO15>0),AC15/AO15,"") | AQ15: =IF(AP15="","",IF(AP15>=2,"A",IF(AP15>=1.2,"B",IF(AP15>=0.6,"C","D"))))
A16: PRE-U3-IN | B16: PRE-U3 | C16: PRE | D16: 46236 | E16: Sunday | F16: All | G16: Built for what needs an ID check. | H16: Promote | I16: Video | J16: Instagram | K16: Mirror | L16: Product tour teaser | M16: Book a demo | N16: No | O16: No | P16: Not started | Q16: Not started | V16: =IF(U16="","",IF(U16>=70,"Pass","Hold")) | W16: 46236 | X16: 10:00 AM | Y16: Scheduled | AM16: No | AP16: =IF(AND(AC16<>"",AO16<>"",AO16>0),AC16/AO16,"") | AQ16: =IF(AP16="","",IF(AP16>=2,"A",IF(AP16>=1.2,"B",IF(AP16>=0.6,"C","D"))))
A17: PRE-U4-LI | B17: PRE-U4 | C17: PRE | D17: 46236 | E17: Sunday | F17: All | G17: Built for what needs an ID check. | H17: Educate | I17: Static | J17: LinkedIn | K17: Primary | L17: What's Included page goes live | M17: Read more (link) | N17: No | O17: No | P17: Not started | Q17: Not started | V17: =IF(U17="","",IF(U17>=70,"Pass","Hold")) | W17: 46236 | X17: 10:00 AM | Y17: Scheduled | AM17: No | AP17: =IF(AND(AC17<>"",AO17<>"",AO17>0),AC17/AO17,"") | AQ17: =IF(AP17="","",IF(AP17>=2,"A",IF(AP17>=1.2,"B",IF(AP17>=0.6,"C","D"))))
... A24: PRE-U5-TH | B24: PRE-U5 | C24: PRE | D24: 46237 | E24: Monday | F24: All | G24: A quote built around your store, not a shelf price. | H24: Engage | I24: Static | J24: Threads | K24: Primary | L24: The pricing-question post, pinned | M24: Comment or DM for a call | N24: No | O24: No | P24: Not started | Q24: Not started | V24: =IF(U24="","",IF(U24>=70,"Pass","Hold")) | W24: 46237 | X24: 10:00 AM | Y24: Scheduled | AM24: No | AP24: =IF(AND(AC24<>"",AO24<>"",AO24>0),AC24/AO24,"") | AQ24: =IF(AP24="","",IF(AP24>=2,"A",IF(AP24>=1.2,"B",IF(AP24>=0.6,"C","D"))))
A25: W01-U1-LI | B25: W01-U1 | C25: 1 | D25: 46237 | E25: Monday | F25: Danny | G25: Built for what needs an ID check. | H25: Educate | I25: Text | J25: LinkedIn | K25: Primary | L25: What's actually included with RetailzPOS | M25: Read more (link) | N25: No | O25: No | P25: Not started | Q25: Not started | V25: =IF(U25="","",IF(U25>=70,"Pass","Hold")) | W25: 46237 | X25: 10:00 AM | Y25: Scheduled | AM25: No | AP25: =IF(AND(AC25<>"",AO25<>"",AO25>0),AC25/AO25,"") | AQ25: =IF(AP25="","",IF(AP25>=2,"A",IF(AP25>=1.2,"B",IF(AP25>=0.6,"C","D"))))
A26: W01-U1-FA | B26: W01-U1 | C26: 1 | D26: 46237 | E26: Monday | F26: Danny | G26: Built for what needs an ID check. | H26: Educate | I26: Text | J26: Facebook | K26: Primary | L26: What's actually included with RetailzPOS | M26: Read more (link) | N26: No | O26: No | P26: Not started | Q26: Not started | V26: =IF(U26="","",IF(U26>=70,"Pass","Hold")) | W26: 46237 | X26: 10:00 AM | Y26: Scheduled | AM26: No | AP26: =IF(AND(AC26<>"",AO26<>"",AO26>0),AC26/AO26,"") | AQ26: =IF(AP26="","",IF(AP26>=2,"A",IF(AP26>=1.2,"B",IF(AP26>=0.6,"C","D"))))
A27: W01-U1-BL | B27: W01-U1 | C27: 1 | D27: 46237 | E27: Monday | F27: Danny | G27: Built for what needs an ID check. | H27: Educate | I27: Text | J27: Blog/SEO | K27: Primary | L27: What's actually included with RetailzPOS | M27: Read more (link) | N27: No | O27: No | P27: Not started | Q27: Not started | V27: =IF(U27="","",IF(U27>=70,"Pass","Hold")) | W27: 46237 | X27: 10:00 AM | Y27: Scheduled | AM27: No | AP27: =IF(AND(AC27<>"",AO27<>"",AO27>0),AC27/AO27,"") | AQ27: =IF(AP27="","",IF(AP27>=2,"A",IF(AP27>=1.2,"B",IF(AP27>=0.6,"C","D"))))
A28: W01-U1-X | B28: W01-U1 | C28: 1 | D28: 46237 | E28: Monday | F28: Danny | G28: Built for what needs an ID check. | H28: Educate | I28: Text | J28: X | K28: Mirror | L28: What's actually included with RetailzPOS | M28: Read more (link) | N28: No | O28: No | P28: Not started | Q28: Not started | V28: =IF(U28="","",IF(U28>=70,"Pass","Hold")) | W28: 46237 | X28: 10:00 AM | Y28: Scheduled | AM28: No | AP28: =IF(AND(AC28<>"",AO28<>"",AO28>0),AC28/AO28,"") | AQ28: =IF(AP28="","",IF(AP28>=2,"A",IF(AP28>=1.2,"B",IF(AP28>=0.6,"C","D"))))
A29: W01-U2-IN | B29: W01-U2 | C29: 1 | D29: 46238 | E29: Tuesday | F29: Danny | G29: Built for what needs an ID check. | H29: Educate | I29: Carousel | J29: Instagram | K29: Primary | L29: Hard-block age verification, the 3-Layer way | M29: Book a demo | N29: No | O29: No | P29: Not started | Q29: Not started | V29: =IF(U29="","",IF(U29>=70,"Pass","Hold")) | W29: 46238 | X29: 10:00 AM | Y29: Scheduled | AM29: No | AP29: =IF(AND(AC29<>"",AO29<>"",AO29>0),AC29/AO29,"") | AQ29: =IF(AP29="","",IF(AP29>=2,"A",IF(AP29>=1.2,"B",IF(AP29>=0.6,"C","D"))))
A30: W01-U2-FA | B30: W01-U2 | C30: 1 | D30: 46238 | E30: Tuesday | F30: Danny | G30: Built for what needs an ID check. | H30: Educate | I30: Carousel | J30: Facebook | K30: Mirror | L30: Hard-block age verification, the 3-Layer way | M30: Book a demo | N30: No | O30: No | P30: Not started | Q30: Not started | V30: =IF(U30="","",IF(U30>=70,"Pass","Hold")) | W30: 46238 | X30: 10:00 AM | Y30: Scheduled | AM30: No | AP30: =IF(AND(AC30<>"",AO30<>"",AO30>0),AC30/AO30,"") | AQ30: =IF(AP30="","",IF(AP30>=2,"A",IF(AP30>=1.2,"B",IF(AP30>=0.6,"C","D"))))
A31: W01-U2-LI | B31: W01-U2 | C31: 1 | D31: 46238 | E31: Tuesday | F31: Danny | G31: Built for what needs an ID check. | H31: Educate | I31: Carousel | J31: LinkedIn | K31: Adapted | L31: Hard-block age verification, the 3-Layer way | M31: Book a demo | N31: No | O31: No | P31: Not started | Q31: Not started | V31: =IF(U31="","",IF(U31>=70,"Pass","Hold")) | W31: 46238 | X31: 10:00 AM | Y31: Scheduled | AM31: No | AP31: =IF(AND(AC31<>"",AO31<>"",AO31>0),AC31/AO31,"") | AQ31: =IF(AP31="","",IF(AP31>=2,"A",IF(AP31>=1.2,"B",IF(AP31>=0.6,"C","D"))))
A32: W01-U3-TI | B32: W01-U3 | C32: 1 | D32: 46239 | E32: Wednesday | F32: Danny | G32: Built for what needs an ID check. | H32: Inspire | I32: Video | J32: TikTok | K32: Primary | L32: A day behind the counter | M32: Book a demo | N32: No | O32: No | P32: Not started | Q32: Not started | V32: =IF(U32="","",IF(U32>=70,"Pass","Hold")) | W32: 46239 | X32: 10:00 AM | Y32: Scheduled | AM32: No | AP32: =IF(AND(AC32<>"",AO32<>"",AO32>0),AC32/AO32,"") | AQ32: =IF(AP32="","",IF(AP32>=2,"A",IF(AP32>=1.2,"B",IF(AP32>=0.6,"C","D"))))
A33: W01-U3-IN | B33: W01-U3 | C33: 1 | D33: 46239 | E33: Wednesday | F33: Danny | G33: Built for what needs an ID check. | H33: Inspire | I33: Video | J33: Instagram | K33: Mirror | L33: A day behind the counter | M33: Book a demo | N33: No | O33: No | P33: Not started | Q33: Not started | V33: =IF(U33="","",IF(U33>=70,"Pass","Hold")) | W33: 46239 | X33: 10:00 AM | Y33: Scheduled | AM33: No | AP33: =IF(AND(AC33<>"",AO33<>"",AO33>0),AC33/AO33,"") | AQ33: =IF(AP33="","",IF(AP33>=2,"A",IF(AP33>=1.2,"B",IF(AP33>=0.6,"C","D"))))
A34: W01-U4-LI | B34: W01-U4 | C34: 1 | D34: 46240 | E34: Thursday | F34: Danny | G34: Built for what needs an ID check. | H34: Engage | I34: Static | J34: LinkedIn | K34: Primary | L34: The 11pm ID check | M34: Book a demo | N34: No | O34: No | P34: Not started | Q34: Not started | V34: =IF(U34="","",IF(U34>=70,"Pass","Hold")) | W34: 46240 | X34: 10:00 AM | Y34: Scheduled | AM34: No | AP34: =IF(AND(AC34<>"",AO34<>"",AO34>0),AC34/AO34,"") | AQ34: =IF(AP34="","",IF(AP34>=2,"A",IF(AP34>=1.2,"B",IF(AP34>=0.6,"C","D"))))
A35: W01-U4-FA | B35: W01-U4 | C35: 1 | D35: 46240 | E35: Thursday | F35: Danny | G35: Built for what needs an ID check. | H35: Engage | I35: Static | J35: Facebook | K35: Mirror | L35: The 11pm ID check | M35: Book a demo | N35: No | O35: No | P35: Not started | Q35: Not started | V35: =IF(U35="","",IF(U35>=70,"Pass","Hold")) | W35: 46240 | X35: 10:00 AM | Y35: Scheduled | AM35: No | AP35: =IF(AND(AC35<>"",AO35<>"",AO35>0),AC35/AO35,"") | AQ35: =IF(AP35="","",IF(AP35>=2,"A",IF(AP35>=1.2,"B",IF(AP35>=0.6,"C","D"))))
A36: W01-U4-IN | B36: W01-U4 | C36: 1 | D36: 46240 | E36: Thursday | F36: Danny | G36: Built for what needs an ID check. | H36: Engage | I36: Static | J36: Instagram | K36: Adapted | L36: The 11pm ID check | M36: Book a demo | N36: No | O36: No | P36: Not started | Q36: Not started | V36: =IF(U36="","",IF(U36>=70,"Pass","Hold")) | W36: 46240 | X36: 10:00 AM | Y36: Scheduled | AM36: No | AP36: =IF(AND(AC36<>"",AO36<>"",AO36>0),AC36/AO36,"") | AQ36: =IF(AP36="","",IF(AP36>=2,"A",IF(AP36>=1.2,"B",IF(AP36>=0.6,"C","D"))))
... A258: W13-U7-X | B258: W13-U7 | C258: 13 | D258: 46327 | E258: Sunday | F258: All | G258: A quote built around your store, not a shelf price. | H258: Promote | I258: Static | J258: X | K258: Primary | L258: Demo day reminder (bonus) | M258: Join now | N258: No | O258: No | P258: Not started | Q258: Not started | V258: =IF(U258="","",IF(U258>=70,"Pass","Hold")) | W258: 46327 | X258: 10:00 AM | Y258: Scheduled | AM258: No | AP258: =IF(AND(AC258<>"",AO258<>"",AO258>0),AC258/AO258,"") | AQ258: =IF(AP258="","",IF(AP258>=2,"A",IF(AP258>=1.2,"B",IF(AP258>=0.6,"C","D"))))

Sheet Platform Metric Guide
A1: Platform Metric Guide
A2: How engagement compares across platforms, so performance is judged fairly.
A4: Platform | B4: Engagement Signal | C4: Approx. Weight vs. a Like/Reaction | D4: Read this as...
A5: Instagram | B5: Like | C5: 1x (baseline) | D5: Passive approval — cheap, low-signal.
A6: Instagram | B6: Comment | C6: 3x | D6: Real engagement — someone stopped to type.
A7: Instagram | B7: Save | C7: 3x | D7: Intent to return to this later — the strongest passive signal on IG.
A8: Instagram | B8: Share/Send | C8: 4x | D8: The strongest active signal — someone chose to hand this to another person.
A9: Facebook | B9: Reaction | C9: 1x (baseline) | D9: Passive approval.
A10: Facebook | B10: Comment | C10: 3x | D10: Real engagement, especially in local-group contexts.
A11: Facebook | B11: Share | C11: 4x | D11: Highest-intent Facebook signal.
A12: LinkedIn | B12: Reaction | C12: 1x (baseline) | D12: Passive approval — lower-effort on LinkedIn than a comment.
A13: LinkedIn | B13: Comment | C13: 4x | D13: Real engagement — LinkedIn comments carry unusually high algorithmic weight.
A14: LinkedIn | B14: Save | C14: 5x | D14: The single strongest B2B research-intent signal — treat as a hot lead indicator.
A15: LinkedIn | B15: Repost | C15: 4x | D15: High-intent share among a professional audience.
... A22: X / Threads | B22: Repost | C22: 3x | D22: Share-equivalent, mirror-channel context.

Sheet Performance Dashboard
A1: Performance Dashboard
A2: Top-line rollups, pulled live from the 90-Day Calendar & Tracker sheet.
A4: Metric | B4: Value
A5: Total posts scheduled this quarter | B5: =COUNTA('90-Day Calendar & Tracker'!A6:A259)-1
A6: Posts published to date | B6: =COUNTIF('90-Day Calendar & Tracker'!Y6:Y258,"Published")
A7: Posts still scheduled | B7: =COUNTIF('90-Day Calendar & Tracker'!Y6:Y258,"Scheduled")
A8: Posts delayed | B8: =COUNTIF('90-Day Calendar & Tracker'!Y6:Y258,"Delayed")
A9: Average pre-publish score | B9: =IFERROR(AVERAGE('90-Day Calendar & Tracker'!U6:U258),"")
A10: Grade A posts | B10: =COUNTIF('90-Day Calendar & Tracker'!AQ6:AQ258,"A")
A11: Grade B posts | B11: =COUNTIF('90-Day Calendar & Tracker'!AQ6:AQ258,"B")
A12: Grade C posts | B12: =COUNTIF('90-Day Calendar & Tracker'!AQ6:AQ258,"C")
A13: Grade D posts | B13: =COUNTIF('90-Day Calendar & Tracker'!AQ6:AQ258,"D")
A14: Total demo requests attributed | B14: =IFERROR(SUM('90-Day Calendar & Tracker'!AL6:AL258),0)
A15: Compliance-review-required posts still not signed off | B15: =COUNTIFS('90-Day Calendar & Tracker'!N6:N258,"Yes",'90-Day Calendar & Tracker'!AS6:AS258,"")
A16: Rights-clearance-required posts still not cleared | B16: =COUNTIF('90-Day Calendar & Tracker'!O6:O258,"Yes")
A18: Note: rows reference the master Calendar & Tracker sheet directly — this dashboard updates itself as status/performance columns are filled in.

Sheet Weekly Themes
A1: Weekly Themes
A2: The 13-week mindset-ladder map — see Plan Section 10.
A4: Week | B4: Dates | C4: Mindset Stage | D4: Weekly Theme | E4: Lead Persona
A5: 1 | B5: Aug 3–9 | C5: Unaware | D5: Launch grid — What's Included, product tour, review profiles live | E5: Danny
A6: 2 | B6: Aug 10–16 | C6: Unaware → Problem-aware | D6: The 11pm ID check — naming the compliance fear before naming ourselves | E6: Ray
A7: 3 | B7: Aug 17–23 | C7: Problem-aware | D7: The Sunday case-count — shrinkage and case-break inventory pain | E7: Farah
A8: 4 | B8: Aug 24–30 | C8: Problem-aware | D8: The regular who stopped coming — silent churn, no data to see it | E8: Danny
A9: 5 | B9: Aug 31–Sep 6 | C9: Solution-aware (skeptical) | D9: Liquor vertical deep-dive | E9: Danny
A10: 6 | B10: Sep 7–13 | C10: Solution-aware (skeptical) | D10: Convenience vertical deep-dive — multi-location | E10: Farah
A11: 7 | B11: Sep 14–20 | C11: Solution-aware (skeptical) | D11: Smoke/vape vertical deep-dive — SHAFT-aware marketing | E11: Ray
A12: 8 | B12: Sep 21–27 | C12: Solution-aware (skeptical) | D12: CBD vertical deep-dive — the uncontested category | E12: Sam
A13: 9 | B13: Sep 28–Oct 4 | C13: Solution-aware → Product-aware | D13: First proof week — reference-customer story, multi-location growth | E13: Priya
A14: 10 | B14: Oct 5–11 | C14: Product-aware | D14: A day in the store — liquor whole-day workflow story | E14: Danny
A15: 11 | B15: Oct 12–18 | C15: Product-aware | D15: A day in the store — convenience/smoke whole-day workflow story | E15: Farah / Ray
A16: 12 | B16: Oct 19–25 | C16: Product-aware | D16: Flagship benchmark report launch + trade press push | E16: All
A17: 13 | B17: Oct 26–Nov 1 | C17: Product-aware | D17: Open live demo week + Q4 readout | E17: All

Sheet Content Mix Tracker
A1: Content Mix Tracker
A2: Live counts of what's shipped, against the Plan's target mix. Percent columns calculate automatically.
A4: By content pillar category
A5: Category | B5: Target Share | C5: Units Shipped (live count) | D5: Actual Share | E5: Verdict
A6: Educate | B6: 0.35 | C6: =COUNTIF('90-Day Calendar & Tracker'!H6:H258,A6) | D6: =IFERROR(C6/SUM($C$6:$C$10),0) | E6: =IF(ABS(D6-B6)<=0.07,"On target",IF(D6>B6,"Over-weighted","Under-weighted"))
A7: Inspire | B7: 0.25 | C7: =COUNTIF('90-Day Calendar & Tracker'!H6:H258,A7) | D7: =IFERROR(C7/SUM($C$6:$C$10),0) | E7: =IF(ABS(D7-B7)<=0.07,"On target",IF(D7>B7,"Over-weighted","Under-weighted"))
A8: Entertain | B8: 0.1 | C8: =COUNTIF('90-Day Calendar & Tracker'!H6:H258,A8) | D8: =IFERROR(C8/SUM($C$6:$C$10),0) | E8: =IF(ABS(D8-B8)<=0.07,"On target",IF(D8>B8,"Over-weighted","Under-weighted"))
A9: Engage | B9: 0.2 | C9: =COUNTIF('90-Day Calendar & Tracker'!H6:H258,A9) | D9: =IFERROR(C9/SUM($C$6:$C$10),0) | E9: =IF(ABS(D9-B9)<=0.07,"On target",IF(D9>B9,"Over-weighted","Under-weighted"))
A10: Promote | B10: 0.1 | C10: =COUNTIF('90-Day Calendar & Tracker'!H6:H258,A10) | D10: =IFERROR(C10/SUM($C$6:$C$10),0) | E10: =IF(ABS(D10-B10)<=0.07,"On target",IF(D10>B10,"Over-weighted","Under-weighted"))
A12: By format group
A13: Category | B13: Target Share | C13: Units Shipped (live count) | D13: Actual Share | E13: Verdict
A14: Video | B14: 0.3 | C14: =COUNTIF('90-Day Calendar & Tracker'!I6:I258,A14) | D14: =IFERROR(C14/SUM($C$14:$C$17),0) | E14: =IF(ABS(D14-B14)<=0.07,"On target",IF(D14>B14,"Over-weighted","Under-weighted"))
A15: Carousel | B15: 0.25 | C15: =COUNTIF('90-Day Calendar & Tracker'!I6:I258,A15) | D15: =IFERROR(C15/SUM($C$14:$C$17),0) | E15: =IF(ABS(D15-B15)<=0.07,"On target",IF(D15>B15,"Over-weighted","Under-weighted"))
A16: Static | B16: 0.3 | C16: =COUNTIF('90-Day Calendar & Tracker'!I6:I258,A16) | D16: =IFERROR(C16/SUM($C$14:$C$17),0) | E16: =IF(ABS(D16-B16)<=0.07,"On target",IF(D16>B16,"Over-weighted","Under-weighted"))
A17: Text | B17: 0.15 | C17: =COUNTIF('90-Day Calendar & Tracker'!I6:I258,A17) | D17: =IFERROR(C17/SUM($C$14:$C$17),0) | E17: =IF(ABS(D17-B17)<=0.07,"On target",IF(D17>B17,"Over-weighted","Under-weighted"))
A19: By persona
A20: Persona | B20: Units Tagged (live count) | C20: Share of Total
A21: Danny | B21: =COUNTIF('90-Day Calendar & Tracker'!F6:F258,A21) | C21: =IFERROR(B21/253,0)
A22: Farah | B22: =COUNTIF('90-Day Calendar & Tracker'!F6:F258,A22) | C22: =IFERROR(B22/253,0)
A23: Ray | B23: =COUNTIF('90-Day Calendar & Tracker'!F6:F258,A23) | C23: =IFERROR(B23/253,0)
A24: Priya | B24: =COUNTIF('90-Day Calendar & Tracker'!F6:F258,A24) | C24: =IFERROR(B24/253,0)
A25: Sam | B25: =COUNTIF('90-Day Calendar & Tracker'!F6:F258,A25) | C25: =IFERROR(B25/253,0)
A26: All | B26: =COUNTIF('90-Day Calendar & Tracker'!F6:F258,A26) | C26: =IFERROR(B26/253,0)
A27: Farah / Ray | B27: =COUNTIF('90-Day Calendar & Tracker'!F6:F258,A27) | C27: =IFERROR(B27/253,0)

Sheet Feature to Hook Library
A1: Feature to Hook Library
A2: The 3-Layer Method (Feature → Function → Benefit) — see Plan Section 8.
A4: Feature | B4: Function | C4: Benefit ("so you can ___") | D4: Status
A5: Hard-block age verification | B5: Transaction physically cannot complete until a valid ID check passes. | C5: So you can staff confidently — even with a brand-new hire on a Friday night — without one missed check becoming a fine or a license review. | D5: Shipped
A6: Automatic audit logging | B6: Every age-verification check is timestamped and stored without staff having to do anything. | C6: So you can hand over a clean record the moment a regulator or auditor asks, instead of scrambling. | D6: Shipped
A7: Case-break inventory conversion | B7: A case auto-converts to single-unit stock the instant it's broken. | C7: So you can trust the number on the screen instead of recounting the walk-in every week. | D7: Shipped
A8: AI-driven reorder alerts | B8: Flags what's about to run out based on real sales velocity, not a fixed par level. | C8: So you can reorder before the shelf goes empty, not after a customer asks why you're out. | D8: Shipped
A9: Moolah Points win-back automation | B9: Automatically triggers a message once a customer misses their usual visit window. | C9: So you can bring back the regular who quietly stopped coming, without personally remembering to. | D9: Shipped
A10: SHAFT/TCPA-aware campaign templates | B10: Pre-built messaging routes through compliant, category-safe language and consent flows. | C10: So you can market to your list without wondering if today's text is the one that gets you flagged. | D10: Shipped
A11: Dual cash/card pricing | B11: Displays and charges the correct price automatically depending on tender type. | C11: So you can absorb card processing costs fairly, without awkward at-register math. | D11: Shipped
A12: Multi-location unified reporting | B12: One dashboard shows inventory, sales, and loyalty across every store. | C12: So you can open a second or third location without doubling your admin work. | D12: Shipped — confirm current parity before Priya-persona claims (Plan risk #6)
A13: EDI invoicing | B13: Distributor invoices import and reconcile against received stock automatically. | C13: So you can catch a shorted case before it becomes a month-end surprise. | D13: Shipped
A14: Omnichannel/e-commerce sync | B14: Online and in-store inventory stay in sync in real time. | C14: So you can sell online without the fear of a phantom stockout. | D14: Shipped
A15: DO NOT MARKET YET — published support SLA | B15: Any specific response-time commitment. | C15: N/A until confirmed. | D15: BLOCKED — needs Plan Section 23 item 4 sign-off before any claim ships.
A16: DO NOT MARKET YET — blanket CBD compliance | B16: Any "fully compliant in every state" language. | C16: N/A — always route to "confirm your state's current rules." | D16: BLOCKED — needs counsel review, Plan Section 23 item 9.

Sheet Blog & SEO Plan
A1: Blog & SEO Plan
A2: One anchor post per week — see Plan Section 14.
A4: Week | B4: Topic | C4: Intent | D4: Extends / Links To
A5: 1 | B5: What's actually included with RetailzPOS | C5: Self-serve research, no pricing page needed | D5: New: What's Included hub page
A6: 2 | B6: Hard-block vs. soft-block age verification: what the difference actually costs you | C6: Compliance-anxious searchers | D6: Existing compliance/audit-guide content
A7: 3 | B7: Case-break inventory, explained for owners who hate spreadsheets | C7: Shrinkage/inventory-pain searchers | D7: —
A8: 4 | B8: The real cost of a silent churned customer (and how you'd never know) | C8: Loyalty-curious searchers | D8: Moolah Points market research (Paytronix stat)
A9: 5 | B9: Liquor store POS buyer's guide 2026 | C9: Liquor-vertical comparison intent | D9: retailzpos-blog-01 (Bottle POS), -02 (NRS POS), -04 (LMS-POS)
A10: 6 | B10: Convenience store multi-location POS: what actually breaks at scale | C10: Farah-persona, growth-stage intent | D10: retailzpos-blog-06 (Square), -07 (Loyverse)
A11: 7 | B11: SHAFT and TCPA for smoke/vape retail marketing: a plain-English guide | C11: Ray-persona, compliance intent | D11: Existing compliance content
A12: 8 | B12: CBD retail compliance and POS: the state-by-state reality | C12: Sam-persona, uncontested search space | D12: New — requires counsel review
A13: 9 | B13: Customer story: how [reference merchant] cut shrinkage / recovered lapsed customers | C13: Proof-stage, product-aware searchers | D13: New — requires reference customer
A14: 10 | B14: A day in a liquor store running RetailzPOS | C14: Workflow/product-aware searchers | D14: —
A15: 11 | B15: A day in a convenience/smoke shop running RetailzPOS | C15: Workflow/product-aware searchers | D15: —
A16: 12 | B16: The State of Independent Retail POS 2026 — flagship benchmark report | C16: Citation-bait, trade-press pickup, AI-answer-engine sourcing | D16: retailzpos-benchmark-report-groundwork
A17: 13 | B17: Q3 in review: what we learned from this quarter's demos | C17: Bottom-funnel, sets up Q4 | D17: —

Sheet Email & Lifecycle
A1: Email & Lifecycle
A2: See Plan Section 15.
A4: Sequence | B4: Trigger | C4: Goal
A5: Demo-request nurture | B5: Someone requests a demo | C5: Confirm, set expectations, deliver the recorded product tour as a backup if scheduling slips
A6: Post-demo follow-up | B6: Demo held, no close yet | C6: Answer objections by persona/vertical, never lead with price, always end in a next-call invitation
A7: Content digest | B7: Newsletter subscriber | C7: Monthly roundup of vertical deep-dives and benchmark findings, positioned as "worth knowing," not "buy now"
A8: Reference-customer recruitment | B8: Existing merchant flagged as a strong fit | C8: Recruit the 3-5 reference customers needed for Plan Section 23, with a clear, simple usage-rights ask

Sheet Post Grading - Pre
A1: Post Grading — Pre-Publish Scorecard
A2: Weighted out of 100. Truth & Claims Accuracy is a gate — a failing score there stops publication regardless of total. See Plan Section 20.
A4: Criterion | B4: Weight
A5: Truth & claims accuracy (GATE — automatic stop if failed) | B5: 20
A6: Persona relevance (tagged to exactly one of the five) | B6: 12
A7: Messaging-pillar clarity (one pillar, clearly carried) | B7: 12
A8: Hook strength (stops the scroll in the first line/frame) | B8: 12
A9: 3-Layer Method correctly applied (where feature-based) | B9: 10
A10: Compliance-safe language (SHAFT/TCPA/CBD-state caveats as applicable) | B10: 10
A11: No pricing implication anywhere in copy or visual | B11: 8
A12: Visual brand consistency (palette, type, accent cap) | B12: 8
A13: Platform-native formatting | B13: 4
A14: Accessibility (contrast, alt text, no color-only meaning) | B14: 4
A15: Total | B15: =SUM(B5:B14)

Sheet Post Grading - Post
A1: Post Grading — Post-Publish
A2: A/B/C/D grade assigned 48-72 hours after publish, based on reach relative to the account's trailing 30-day median for that format/platform. See Plan Section 21.
A4: Grade | B4: Reach vs. 30-Day Median
A5: A | B5: 2.0x or higher
A6: B | B6: 1.2x – 1.99x
A7: C | B7: 0.6x – 1.19x
A8: D | B8: Below 0.6x
A10: Grades feed the Content Mix Tracker and inform which pillar/format/persona combinations get more or less weight the following month.

Sheet Do & Don't
A1: Content Do's and Don'ts
A2: See Plan Section 19.
A4: Do | B4: Don't
A5: Name the specific pain (the 11pm ID check, the Sunday case-count) before naming RetailzPOS | B5: Open with a generic "grow your business" line that could apply to any POS
A6: Use real, current feature capability, checked against the confirmed matrix | B6: Market a feature that isn't shipped yet, or an SLA that isn't confirmed
A7: Route every "what's this cost?" to a warm answer + demo invite | B7: Ever quote a figure, range, or soft price anchor
A8: Route every CBD compliance claim to "confirm your state's current rules" | B8: Imply blanket CBD legal compliance in every state
A9: Use SHAFT/TCPA-safe language in every SMS-related post and campaign | B9: Name specific nicotine/alcohol products directly inside SMS copy
A10: Tag every post to exactly one of the five named personas | B10: Write a post aimed at "retailers" in the abstract
A11: Use one messaging pillar per post, rotated | B11: Cram multiple pillars into a single post
A12: Credit and get usage rights cleared before using any reference-customer story | B12: Publish a merchant story without signed usage rights
A13: Check alcohol/tobacco/CBD ad policy on the specific platform before any paid spend | B13: Assume Meta/TikTok ad policy is the same as general retail
A14: Keep every claim checkable against real product capability or cited research | B14: State a statistic without a source, internal or external

Sheet KPI Tracker
A1: KPI Tracker
A2: True-north metric: demo requests. No numeric targets before Week 5 — see the Brief's measurement philosophy.
A4: Week | B4: Dates | C4: Reach (total) | D4: Saves/Shares (total) | E4: Avg. Watch-through % | F4: Demo Page Visits | G4: Demo Requests | H4: Demos Held
A5: 1 | B5: Aug 3–9
A6: 2 | B6: Aug 10–16
A7: 3 | B7: Aug 17–23
A8: 4 | B8: Aug 24–30
A9: 5 | B9: Aug 31–Sep 6
A10: 6 | B10: Sep 7–13
A11: 7 | B11: Sep 14–20
A12: 8 | B12: Sep 21–27
A13: 9 | B13: Sep 28–Oct 4
A14: 10 | B14: Oct 5–11
A15: 11 | B15: Oct 12–18
A16: 12 | B16: Oct 19–25
A17: 13 | B17: Oct 26–Nov 1
A18: Month 1 total (Weeks 1-4) | C18: =SUM(C4:C7) | D18: =SUM(D4:D7) | E18: =SUM(E4:E7) | F18: =SUM(F4:F7) | G18: =SUM(G4:G7) | H18: =SUM(H4:H7)
A19: Month 2 total (Weeks 5-9) | C19: =SUM(C8:C12) | D19: =SUM(D8:D12) | E19: =SUM(E8:E12) | F19: =SUM(F8:F12) | G19: =SUM(G8:G12) | H19: =SUM(H8:H12)
A20: Month 3 total (Weeks 10-13) | C20: =SUM(C13:C16) | D20: =SUM(D13:D16) | E20: =SUM(E13:E16) | F20: =SUM(F13:F16) | G20: =SUM(G13:G16) | H20: =SUM(H13:H16)
A21: Quarter total | C21: =SUM(C4:C16) | D21: =SUM(D4:D16) | E21: =SUM(E4:E16) | F21: =SUM(F4:F16) | G21: =SUM(G4:G16) | H21: =SUM(H4:H16)
A23: Per the measurement philosophy: Month 1 (Weeks 1-4) sets the baseline. No numeric weekly targets are set before Week 5 — targets invented before real data are just wishes.
